alu.v
// Shrey Bansal (210997)
// Narendra Singh (210649)

// Module to perform the arithmetic and logical operations
module alu(opcode, funct, shamt, s1, s2, dest, pc, const, pcNew, jumpAddress);

    input [4:0] funct, shamt;
    input [5:0] opcode;
    input [15:0] pc, const;
    input [25:0] jumpAddress;
    input [31:0] s1, s2;
    output reg [15:0] pcNew;
    output reg [31:0] dest;

    always @(*) begin
        
        if(opcode == 0) begin
            if(funct == 0) dest = s1 + s2;
            else if(funct == 1) dest = s1 - s2;
            else if(funct == 2) dest = s1 + s2;
            else if(funct == 3) dest = s1 - s2;
            else if(funct == 4) dest = s1 & s2;
            else if(funct == 5) dest = s1 | s2;
            else if(funct == 6) dest = s2 << shamt;
            else if(funct == 7) dest = s2 >> shamt;
            else if(funct == 8) dest = (s1 < s2 ? 32'd1 : 32'd0);
        end
        else if(opcode == 1) begin
            dest = s2 + {16'd0, const};                   // Will be stored in s1 register
            dest = {16'd0, dest[15:0]};
        end
        else if(opcode == 2) dest = s2 + {16'd0, const};  // Will be stored in s1 register
        else if(opcode == 3) dest = s2 & {16'd0, const};  // Will be stored in s1 register
        else if(opcode == 4) dest = s2 | {16'd0, const};  // Will be stored in s1 register
        else if(opcode == 7) pcNew = (s1 == s2 ? const : pc);
        else if(opcode == 8) pcNew = (s1 != s2 ? const : pc);
        else if(opcode == 9) pcNew = (s1 > s2 ? const : pc);
        else if(opcode == 10) pcNew = (s1 >= s2 ? const : pc);
        else if(opcode == 11) pcNew = (s1 < s2 ? const : pc);
        else if(opcode == 12) pcNew = (s1 <= s2 ? const : pc);
        else if(opcode == 13) pcNew = jumpAddress;
        else if(opcode == 14) pcNew = jumpAddress;
        else if(opcode == 15) pcNew = jumpAddress;
        else if(opcode == 16) dest = (s1 < {16'd0, const} ? 32'd1 : 32'd0);  // Will be stored in s2 register

    end

endmodule

memory.v
// Shrey Bansal (210997)
// Narendra Singh (210649)

// Module to store the Machine Code of the program
module instructions(pc, inst);

    input [15:0] pc;
    output reg [31:0] inst;

    reg [31:0] DF [65535:0];

    initial begin

        // main:
        DF[0] = {6'd5, 5'd28, 5'd19, 16'd0};                // s0 = &arr
        DF[1] = {6'd1, 5'd8, 5'd0, 16'd0};                  // t0 = 0
        DF[2] = {6'd1, 5'd9, 5'd0, 16'd0};                  // t1 = 0
        DF[3] = {6'd1, 5'd20, 5'd0, 16'd11};                // s1 = 11 = size of arr
        DF[4] = {6'd1, 5'd21, 5'd0, 16'd11};                // s2 = 11 = size of arr
        DF[5] = {6'd0, 5'd19, 5'd0, 5'd10, 5'd0, 6'd0};     // t2 = s0 = &arr
        DF[6] = {6'd0, 5'd19, 5'd0, 5'd11, 5'd0, 6'd0};     // t3 = s0 = &arr
        DF[7] = {6'd1, 5'd20, 5'd20, -16'sd1};              // s1 = s1 - 1
        // outer_loop:
        DF[8] = {6'd1, 5'd9, 5'd0, 16'd0};                  // t1 = 0
        DF[9] = {6'd1, 5'd21, 5'd21, -16'sd1};              // s2 = s2 - 1
        DF[10] = {6'd0, 5'd19, 5'd0, 5'd11, 5'd0, 6'd0};    // t3 = s0
        // inner_loop:
        DF[11] = {6'd5, 5'd11, 5'd22, 16'd0};               // s3 = Data[t3]
        DF[12] = {6'd1, 5'd11, 5'd11, 16'd1};               // t3 = t3 + 1
        DF[13] = {6'd5, 5'd11, 5'd23, 16'd0};               // s4 = Data[t3]
        DF[14] = {6'd1, 5'd9, 5'd9, 16'd1};                 // t1 = t1 + 1
        DF[15] = {6'd0, 5'd22, 5'd23, 5'd12, 5'd0, 6'd8};   // t4 = (s3 < s4)
        DF[16] = {6'd8, 5'd12, 5'd0, 16'd20};               // pc = 20 if t4 != 0
        // swap
        DF[17] = {6'd6, 5'd11, 5'd22, 16'd0};               // Data[t3] = s3
        DF[18] = {6'd6, 5'd11, 5'd23, -16'sd1};             // Data[t3 - 1] = s4
        DF[19] = {6'd5, 5'd11, 5'd23, 16'd0};               // s4 = Data[t3]
        // cond
        DF[20] = {6'd8, 5'd9, 5'd21, 16'd11};               // pc = 11 if t1 != s2
        DF[21] = {6'd1, 5'd8, 5'd8, 16'd1};                 // t0 = t0 + 1
        DF[22] = {6'd8, 5'd8, 5'd20, 16'd8};                // pc = 8 if t0 != s1

    end

    always @(*) begin
        
        inst = DF[pc];

    end

endmodule


// MOdule to store the data used in the program
module data(address, dataIn, dataOut, mode);

    input mode;
    input [31:0] dataIn;
    input [15:0] address;
    output reg [31:0] dataOut;

    reg [31:0] DF [65535:0];

    initial begin

        DF[0] = 32'd10;
        DF[1] = 32'd60;
        DF[2] = 32'd40;
        DF[3] = 32'd70;
        DF[4] = 32'd20;
        DF[5] = 32'd30;
        DF[6] = 32'd90;
        DF[7] = 32'd100;
        DF[8] = 32'd0;
        DF[9] = 32'd80;
        DF[10] = 32'd50;
        DF[100] = 32'd0;             // stores the address of arr[0]

        $monitor("%d %d %d %d %d %d %d %d %d %d %d", DF[0], DF[1], DF[2], DF[3], DF[4], DF[5], DF[6], DF[7], DF[8], DF[9], DF[10]);
        // Monitoring each element of the array

    end

    always @(*) begin
        
        if(mode == 0) dataOut = DF[address];
        else DF[address] = dataIn;

    end

endmodule


// Module to store the 30 registers used in the Processor
module registers(add1, add2, writeAdd, writeEn, dataIn, dataOut1, dataOut2);

    input writeEn;
    input [4:0] add1, add2, writeAdd;
    input [31:0] dataIn;
    output reg [31:0] dataOut1, dataOut2;

    reg [31:0] DF [29:0];

    initial begin
        
        for(integer i = 0; i < 30; i = i + 1) begin
            
            DF[i] = 32'd0;

        end

        DF[28] = 32'd100;        // the location in memory storing the address of arr

    end

    always @(*) begin
        
        if(writeEn == 0) begin

            // Read Mode
            dataOut1 = DF[add1];
            dataOut2 = DF[add2];

        end 
        else DF[writeAdd] = dataIn;  // Write Mode

    end

endmodule

cpu.v
// Shrey Bansal (210997)
// Narendra Singh (210649)

`include "alu.v"
`include "memory.v"

// Module for the Control Unit of the Processor
module cpu(clk);

    input clk;

    reg mode, writeEn;
    reg [4:0] funct, shamt, add1, add2, writeAdd, rs, rt, rd;
    reg [5:0] opcode;
    reg [15:0] pc, const, dataAddress;
    reg [25:0] jumpAddress;
    reg [31:0] s1, s2, dataInData, dataInReg;
    wire [15:0] pcNew;
    wire [31:0] dest, inst, dataOutData, dataOutReg1, dataOutReg2;

    instructions instruc(pc, inst);
    data dt(dataAddress, dataInData, dataOutData, mode);
    registers regs(add1, add2, writeAdd, writeEn, dataInReg, dataOutReg1, dataOutReg2);
    alu calc(opcode, funct, shamt, s1, s2, dest, pc, const, pcNew, jumpAddress);

    initial begin
        
        pc = 0;
        writeEn = 0;

    end

    always @(posedge clk) begin
        
        // inst will be fetched on pc change
        // The incoming instruction is parsed
        opcode = inst[31:26];
        rs = inst[25:21];
        rt = inst[20:16];
        rd = inst[15:11];
        shamt = inst[10:6];
        funct = inst[5:0];
        const = inst[15:0];
        jumpAddress = inst[25:0];

        // Fetching rs and rt from registers
        writeEn = 0;
        add1 = rs;
        add2 = rt;
        #10
        s1 = dataOutReg1;
        s2 = dataOutReg2;
        #10

        // send data to alu based on the opcode
        if(opcode == 0) begin
            
            writeEn = 1;
            writeAdd = rd;
            dataInReg = dest;

        end
        else if(opcode <= 4) begin

            writeEn = 1;
            writeAdd = rs;
            dataInReg = dest;

        end
        else if(opcode == 5) begin
            
            // lw
            mode = 0;
            dataAddress = s1 + const;
            #10
            writeEn = 1;
            writeAdd = rt;
            dataInReg = dataOutData;
            
        end
        else if(opcode == 6) begin
            
            // sw
            mode = 1;
            dataAddress = s1 + const;
            dataInData = s2;

        end
        else if(opcode > 12 && opcode < 16) begin
            
            jumpAddress = inst[25:0];

        end
        else if(opcode == 16) begin

            writeEn = 1;
            writeAdd = rt;
            dataInReg = dest;

        end
        #10

        if(opcode >= 7 && opcode <= 15) begin 

            if(pcNew != pc) pc = pcNew - 1;

        end
        pc = pc + 1;

    end

endmodule

cpu_tb.v
// Shrey Bansal (210997)
// Narendra Singh (210649)

`include "cpu.v"

module cpu_tb();

    reg clk;

    initial begin
        clk = 0;
    end
    
    cpu uut(clk);

    always #50 clk = ~clk;

    initial begin
        
        $dumpfile("cpu.vcd");
        $dumpvars(0, cpu_tb);

        #500000  // Time given to complete the execution of the program

        $finish;
    end

endmodule

cpu.vcd
$date
	Sun Apr 16 11:24:53 2023
$end
$version
	Icarus Verilog
$end
$timescale
	1s
$end
$scope module cpu_tb $end
$var reg 1 ! clk $end
$scope module uut $end
$var wire 1 ! clk $end
$var wire 16 " pcNew [15:0] $end
$var wire 32 # inst [31:0] $end
$var wire 32 $ dest [31:0] $end
$var wire 32 % dataOutReg2 [31:0] $end
$var wire 32 & dataOutReg1 [31:0] $end
$var wire 32 ' dataOutData [31:0] $end
$var reg 5 ( add1 [4:0] $end
$var reg 5 ) add2 [4:0] $end
$var reg 16 * const [15:0] $end
$var reg 16 + dataAddress [15:0] $end
$var reg 32 , dataInData [31:0] $end
$var reg 32 - dataInReg [31:0] $end
$var reg 5 . funct [4:0] $end
$var reg 26 / jumpAddress [25:0] $end
$var reg 1 0 mode $end
$var reg 6 1 opcode [5:0] $end
$var reg 16 2 pc [15:0] $end
$var reg 5 3 rd [4:0] $end
$var reg 5 4 rs [4:0] $end
$var reg 5 5 rt [4:0] $end
$var reg 32 6 s1 [31:0] $end
$var reg 32 7 s2 [31:0] $end
$var reg 5 8 shamt [4:0] $end
$var reg 5 9 writeAdd [4:0] $end
$var reg 1 : writeEn $end
$scope module calc $end
$var wire 16 ; const [15:0] $end
$var wire 5 < funct [4:0] $end
$var wire 26 = jumpAddress [25:0] $end
$var wire 6 > opcode [5:0] $end
$var wire 16 ? pc [15:0] $end
$var wire 32 @ s1 [31:0] $end
$var wire 32 A s2 [31:0] $end
$var wire 5 B shamt [4:0] $end
$var reg 32 C dest [31:0] $end
$var reg 16 D pcNew [15:0] $end
$upscope $end
$scope module dt $end
$var wire 16 E address [15:0] $end
$var wire 32 F dataIn [31:0] $end
$var wire 1 0 mode $end
$var reg 32 G dataOut [31:0] $end
$upscope $end
$scope module instruc $end
$var wire 16 H pc [15:0] $end
$var reg 32 I inst [31:0] $end
$upscope $end
$scope module regs $end
$var wire 5 J add1 [4:0] $end
$var wire 5 K add2 [4:0] $end
$var wire 32 L dataIn [31:0] $end
$var wire 5 M writeAdd [4:0] $end
$var wire 1 : writeEn $end
$var reg 32 N dataOut1 [31:0] $end
$var reg 32 O dataOut2 [31:0] $end
$scope begin $ivl_for_loop0 $end
$var integer 32 P i [31:0] $end
$upscope $end
$upscope $end
$upscope $end
$upscope $end
$enddefinitions $end
$comment Show the parameter values. $end
$dumpall
$end
#0
$dumpvars
b11110 P
bx O
bx N
bx M
bx L
bx K
bx J
b10111100100110000000000000000 I
b0 H
bx G
bx F
bx E
bx D
bx C
bx B
bx A
bx @
b0 ?
bx >
bx =
bx <
bx ;
0:
bx 9
bx 8
bx 7
bx 6
bx 5
bx 4
bx 3
b0 2
bx 1
x0
bx /
bx .
bx -
bx ,
bx +
bx *
bx )
bx (
bx '
bx &
bx %
bx $
b10111100100110000000000000000 #
bx "
0!
$end
#50
b0 %
b0 O
b1100100 &
b1100100 N
b10011 )
b10011 K
b11100 (
b11100 J
b11100100110000000000000000 /
b11100100110000000000000000 =
b0 *
b0 ;
b0 .
b0 <
b0 8
b0 B
b0 3
b10011 5
b11100 4
b101 1
b101 >
1!
#60
b0 7
b0 A
b1100100 6
b1100100 @
#70
b0 '
b0 G
b1100100 +
b1100100 E
00
#80
b0 -
b0 L
b10011 9
b10011 M
1:
#90
b101000000000000000000000000 #
b101000000000000000000000000 I
b1 2
b1 ?
b1 H
#100
0!
#150
b0 &
b0 N
b0 $
b0 C
b0 )
b0 K
b1000 (
b1000 J
0:
b1000000000000000000000000 /
b1000000000000000000000000 =
b0 5
b1000 4
b1 1
b1 >
1!
#160
b0 6
b0 @
#170
b1000 9
b1000 M
1:
#180
b101001000000000000000000000 #
b101001000000000000000000000 I
b10 2
b10 ?
b10 H
#200
0!
#250
b1001 (
b1001 J
0:
b1001000000000000000000000 /
b1001000000000000000000000 =
b1001 4
1!
#270
b1001 9
b1001 M
1:
#280
b110100000000000000000001011 #
b110100000000000000000001011 I
b11 2
b11 ?
b11 H
#300
0!
#350
b1011 $
b1011 C
b10100 (
b10100 J
0:
b10100000000000000000001011 /
b10100000000000000000001011 =
b1011 *
b1011 ;
b1011 .
b1011 <
b10100 4
1!
#370
b1011 -
b1011 L
b10100 9
b10100 M
1:
#380
b110101000000000000000001011 #
b110101000000000000000001011 I
b100 2
b100 ?
b100 H
#400
0!
#450
b10101 (
b10101 J
0:
b10101000000000000000001011 /
b10101000000000000000001011 =
b10101 4
1!
#470
b10101 9
b10101 M
1:
#480
b10011000000101000000000000 #
b10011000000101000000000000 I
b101 2
b101 ?
b101 H
#500
0!
#550
b0 $
b0 C
b10011 (
b10011 J
0:
b10011000000101000000000000 /
b10011000000101000000000000 =
b101000000000000 *
b101000000000000 ;
b0 .
b0 <
b1010 3
b10011 4
b0 1
b0 >
1!
#570
b0 -
b0 L
b1010 9
b1010 M
1:
#580
b10011000000101100000000000 #
b10011000000101100000000000 I
b110 2
b110 ?
b110 H
#600
0!
#650
0:
b10011000000101100000000000 /
b10011000000101100000000000 =
b101100000000000 *
b101100000000000 ;
b1011 3
1!
#670
b1011 9
b1011 M
1:
#680
b110100101001111111111111111 #
b110100101001111111111111111 I
b111 2
b111 ?
b111 H
#700
0!
#750
b1011 %
b1011 O
b1011 &
b1011 N
b1111111111111111 $
b1111111111111111 C
b10100 )
b10100 K
b10100 (
b10100 J
0:
b10100101001111111111111111 /
b10100101001111111111111111 =
b1111111111111111 *
b1111111111111111 ;
b11111 .
b11111 <
b11111 8
b11111 B
b11111 3
b10100 5
b10100 4
b1 1
b1 >
1!
#760
b1010 $
b1010 C
b1011 7
b1011 A
b1011 6
b1011 @
#770
b1010 -
b1010 L
b10100 9
b10100 M
1:
#780
b1010 $
b1010 C
b101001000000000000000000000 #
b101001000000000000000000000 I
b1000 2
b1000 ?
b1000 H
#800
0!
#850
b0 %
b0 O
b0 &
b0 N
b1011 $
b1011 C
b0 )
b0 K
b1001 (
b1001 J
0:
b1001000000000000000000000 /
b1001000000000000000000000 =
b0 *
b0 ;
b0 .
b0 <
b0 8
b0 B
b0 3
b0 5
b1001 4
1!
#860
b0 $
b0 C
b0 7
b0 A
b0 6
b0 @
#870
b0 -
b0 L
b1001 9
b1001 M
1:
#880
b110101101011111111111111111 #
b110101101011111111111111111 I
b1001 2
b1001 ?
b1001 H
#900
0!
#950
b1011 %
b1011 O
b1011 &
b1011 N
b1111111111111111 $
b1111111111111111 C
b10101 )
b10101 K
b10101 (
b10101 J
0:
b10101101011111111111111111 /
b10101101011111111111111111 =
b1111111111111111 *
b1111111111111111 ;
b11111 .
b11111 <
b11111 8
b11111 B
b11111 3
b10101 5
b10101 4
1!
#960
b1010 $
b1010 C
b1011 7
b1011 A
b1011 6
b1011 @
#970
b1010 -
b1010 L
b10101 9
b10101 M
1:
#980
b1010 $
b1010 C
b10011000000101100000000000 #
b10011000000101100000000000 I
b1010 2
b1010 ?
b1010 H
#1000
0!
#1050
b0 %
b0 O
b0 &
b0 N
b10110 $
b10110 C
b0 )
b0 K
b10011 (
b10011 J
0:
b10011000000101100000000000 /
b10011000000101100000000000 =
b101100000000000 *
b101100000000000 ;
b0 .
b0 <
b0 8
b0 B
b1011 3
b0 5
b10011 4
b0 1
b0 >
1!
#1060
b0 $
b0 C
b0 7
b0 A
b0 6
b0 @
#1070
b0 -
b0 L
b1011 9
b1011 M
1:
#1080
b10101011101100000000000000000 #
b10101011101100000000000000000 I
b1011 2
b1011 ?
b1011 H
#1100
0!
#1150
b10110 )
b10110 K
b1011 (
b1011 J
0:
b1011101100000000000000000 /
b1011101100000000000000000 =
b0 *
b0 ;
b0 3
b10110 5
b1011 4
b101 1
b101 >
1!
#1170
b1010 '
b1010 G
b0 +
b0 E
#1180
b1010 -
b1010 L
b10110 9
b10110 M
1:
#1190
b101011010110000000000000001 #
b101011010110000000000000001 I
b1100 2
b1100 ?
b1100 H
#1200
0!
#1250
b1 $
b1 C
b1011 )
b1011 K
0:
b1011010110000000000000001 /
b1011010110000000000000001 =
b1 *
b1 ;
b1 .
b1 <
b1011 5
b1 1
b1 >
1!
#1270
b1 -
b1 L
b1011 9
b1011 M
1:
#1280
b10101011101110000000000000000 #
b10101011101110000000000000000 I
b1101 2
b1101 ?
b1101 H
#1300
0!
#1350
b1 &
b1 N
b10111 )
b10111 K
0:
b1011101110000000000000000 /
b1011101110000000000000000 =
b0 *
b0 ;
b0 .
b0 <
b10111 5
b101 1
b101 >
1!
#1360
b1 6
b1 @
#1370
b111100 '
b111100 G
b1 +
b1 E
#1380
b111100 -
b111100 L
b10111 9
b10111 M
1:
#1390
b101001010010000000000000001 #
b101001010010000000000000001 I
b1110 2
b1110 ?
b1110 H
#1400
0!
#1450
b0 &
b0 N
b1001 )
b1001 K
b1001 (
b1001 J
0:
b1001010010000000000000001 /
b1001010010000000000000001 =
b1 *
b1 ;
b1 .
b1 <
b1001 5
b1001 4
b1 1
b1 >
1!
#1460
b0 6
b0 @
#1470
b1 -
b1 L
b1001 9
b1001 M
1:
#1480
b10110101110110000000001000 #
b10110101110110000000001000 I
b1111 2
b1111 ?
b1111 H
#1500
0!
#1550
b111100 %
b111100 O
b1010 &
b1010 N
b0 $
b0 C
b10111 )
b10111 K
b10110 (
b10110 J
0:
b10110101110110000000001000 /
b10110101110110000000001000 =
b110000000001000 *
b110000000001000 ;
b1000 .
b1000 <
b1100 3
b10111 5
b10110 4
b0 1
b0 >
1!
#1560
b1 $
b1 C
b111100 7
b111100 A
b1010 6
b1010 @
#1570
b1100 9
b1100 M
1:
#1580
b100001100000000000000000010100 #
b100001100000000000000000010100 I
b10000 2
b10000 ?
b10000 H
#1600
0!
#1650
b0 %
b0 O
b1 &
b1 N
b10100 "
b10100 D
b0 )
b0 K
b1100 (
b1100 J
0:
b1100000000000000000010100 /
b1100000000000000000010100 =
b10100 *
b10100 ;
b10100 .
b10100 <
b0 3
b0 5
b1100 4
b1000 1
b1000 >
1!
#1660
b0 7
b0 A
b1 6
b1 @
#1680
b100001001101010000000000001011 #
b100001001101010000000000001011 I
b10100 2
b10100 ?
b10100 H
#1700
0!
#1750
b1010 %
b1010 O
b1011 "
b1011 D
b10101 )
b10101 K
b1001 (
b1001 J
b1001101010000000000001011 /
b1001101010000000000001011 =
b1011 *
b1011 ;
b1011 .
b1011 <
b10101 5
b1001 4
1!
#1760
b1010 7
b1010 A
#1780
b10101011101100000000000000000 #
b10101011101100000000000000000 I
b1011 2
b1011 ?
b1011 H
#1800
0!
#1850
b10110 )
b10110 K
b1011 (
b1011 J
b1011101100000000000000000 /
b1011101100000000000000000 =
b0 *
b0 ;
b0 .
b0 <
b10110 5
b1011 4
b101 1
b101 >
1!
#1880
b111100 -
b111100 L
b10110 9
b10110 M
1:
#1890
b101011010110000000000000001 #
b101011010110000000000000001 I
b1100 2
b1100 ?
b1100 H
#1900
0!
#1950
b1 %
b1 O
b1011 $
b1011 C
b1011 )
b1011 K
0:
b1011010110000000000000001 /
b1011010110000000000000001 =
b1 *
b1 ;
b1 .
b1 <
b1011 5
b1 1
b1 >
1!
#1960
b10 $
b10 C
b1 7
b1 A
#1970
b10 -
b10 L
b1011 9
b1011 M
1:
#1980
b10101011101110000000000000000 #
b10101011101110000000000000000 I
b1101 2
b1101 ?
b1101 H
#2000
0!
#2050
b111100 %
b111100 O
b10 &
b10 N
b10111 )
b10111 K
0:
b1011101110000000000000000 /
b1011101110000000000000000 =
b0 *
b0 ;
b0 .
b0 <
b10111 5
b101 1
b101 >
1!
#2060
b111100 7
b111100 A
b10 6
b10 @
#2070
b101000 '
b101000 G
b10 +
b10 E
#2080
b101000 -
b101000 L
b10111 9
b10111 M
1:
#2090
b101001010010000000000000001 #
b101001010010000000000000001 I
b1110 2
b1110 ?
b1110 H
#2100
0!
#2150
b1 %
b1 O
b1 &
b1 N
b111101 $
b111101 C
b1001 )
b1001 K
b1001 (
b1001 J
0:
b1001010010000000000000001 /
b1001010010000000000000001 =
b1 *
b1 ;
b1 .
b1 <
b1001 5
b1001 4
b1 1
b1 >
1!
#2160
b10 $
b10 C
b1 7
b1 A
b1 6
b1 @
#2170
b10 -
b10 L
b1001 9
b1001 M
1:
#2180
b10110101110110000000001000 #
b10110101110110000000001000 I
b1111 2
b1111 ?
b1111 H
#2200
0!
#2250
b101000 %
b101000 O
b111100 &
b111100 N
b0 $
b0 C
b10111 )
b10111 K
b10110 (
b10110 J
0:
b10110101110110000000001000 /
b10110101110110000000001000 =
b110000000001000 *
b110000000001000 ;
b1000 .
b1000 <
b1100 3
b10111 5
b10110 4
b0 1
b0 >
1!
#2260
b101000 7
b101000 A
b111100 6
b111100 @
#2270
b0 -
b0 L
b1100 9
b1100 M
1:
#2280
b100001100000000000000000010100 #
b100001100000000000000000010100 I
b10000 2
b10000 ?
b10000 H
#2300
0!
#2350
b0 %
b0 O
b0 &
b0 N
b10100 "
b10100 D
b0 )
b0 K
b1100 (
b1100 J
0:
b1100000000000000000010100 /
b1100000000000000000010100 =
b10100 *
b10100 ;
b10100 .
b10100 <
b0 3
b0 5
b1100 4
b1000 1
b1000 >
1!
#2360
b10000 "
b10000 D
b0 7
b0 A
b0 6
b0 @
#2380
b10001 "
b10001 D
b11001011101100000000000000000 #
b11001011101100000000000000000 I
b10001 2
b10001 ?
b10001 H
#2400
0!
#2450
b111100 %
b111100 O
b10 &
b10 N
b10110 )
b10110 K
b1011 (
b1011 J
b1011101100000000000000000 /
b1011101100000000000000000 =
b0 *
b0 ;
b0 .
b0 <
b10110 5
b1011 4
b110 1
b110 >
1!
#2460
b111100 7
b111100 A
b10 6
b10 @
#2470
b111100 ,
b111100 F
10
#2480
b11001011101111111111111111111 #
b11001011101111111111111111111 I
b10010 2
b10010 ?
b10010 H
#2500
0!
#2550
b101000 %
b101000 O
b10111 )
b10111 K
b1011101111111111111111111 /
b1011101111111111111111111 =
b1111111111111111 *
b1111111111111111 ;
b11111 .
b11111 <
b11111 8
b11111 B
b11111 3
b10111 5
1!
#2560
b101000 7
b101000 A
#2570
b101000 ,
b101000 F
b1 +
b1 E
#2580
b10101011101110000000000000000 #
b10101011101110000000000000000 I
b10011 2
b10011 ?
b10011 H
#2600
0!
#2650
b1011101110000000000000000 /
b1011101110000000000000000 =
b0 *
b0 ;
b0 .
b0 <
b0 8
b0 B
b0 3
b101 1
b101 >
1!
#2670
b111100 '
b111100 G
b10 +
b10 E
00
#2680
b111100 -
b111100 L
b10111 9
b10111 M
1:
#2690
b100001001101010000000000001011 #
b100001001101010000000000001011 I
b10100 2
b10100 ?
b10100 H
#2700
0!
#2750
b1010 %
b1010 O
b1011 "
b1011 D
b10101 )
b10101 K
b1001 (
b1001 J
0:
b1001101010000000000001011 /
b1001101010000000000001011 =
b1011 *
b1011 ;
b1011 .
b1011 <
b10101 5
b1001 4
b1000 1
b1000 >
1!
#2760
b1010 7
b1010 A
#2780
b10101011101100000000000000000 #
b10101011101100000000000000000 I
b1011 2
b1011 ?
b1011 H
#2800
0!
#2850
b111100 %
b111100 O
b10110 )
b10110 K
b1011 (
b1011 J
b1011101100000000000000000 /
b1011101100000000000000000 =
b0 *
b0 ;
b0 .
b0 <
b10110 5
b1011 4
b101 1
b101 >
1!
#2860
b111100 7
b111100 A
#2880
b10110 9
b10110 M
1:
#2890
b101011010110000000000000001 #
b101011010110000000000000001 I
b1100 2
b1100 ?
b1100 H
#2900
0!
#2950
b10 %
b10 O
b111101 $
b111101 C
b1011 )
b1011 K
0:
b1011010110000000000000001 /
b1011010110000000000000001 =
b1 *
b1 ;
b1 .
b1 <
b1011 5
b1 1
b1 >
1!
#2960
b11 $
b11 C
b10 7
b10 A
#2970
b11 -
b11 L
b1011 9
b1011 M
1:
#2980
b10101011101110000000000000000 #
b10101011101110000000000000000 I
b1101 2
b1101 ?
b1101 H
#3000
0!
#3050
b111100 %
b111100 O
b11 &
b11 N
b10111 )
b10111 K
0:
b1011101110000000000000000 /
b1011101110000000000000000 =
b0 *
b0 ;
b0 .
b0 <
b10111 5
b101 1
b101 >
1!
#3060
b111100 7
b111100 A
b11 6
b11 @
#3070
b1000110 '
b1000110 G
b11 +
b11 E
#3080
b1000110 -
b1000110 L
b10111 9
b10111 M
1:
#3090
b101001010010000000000000001 #
b101001010010000000000000001 I
b1110 2
b1110 ?
b1110 H
#3100
0!
#3150
b10 %
b10 O
b10 &
b10 N
b111101 $
b111101 C
b1001 )
b1001 K
b1001 (
b1001 J
0:
b1001010010000000000000001 /
b1001010010000000000000001 =
b1 *
b1 ;
b1 .
b1 <
b1001 5
b1001 4
b1 1
b1 >
1!
#3160
b11 $
b11 C
b10 7
b10 A
b10 6
b10 @
#3170
b11 -
b11 L
b1001 9
b1001 M
1:
#3180
b10110101110110000000001000 #
b10110101110110000000001000 I
b1111 2
b1111 ?
b1111 H
#3200
0!
#3250
b1000110 %
b1000110 O
b111100 &
b111100 N
b0 $
b0 C
b10111 )
b10111 K
b10110 (
b10110 J
0:
b10110101110110000000001000 /
b10110101110110000000001000 =
b110000000001000 *
b110000000001000 ;
b1000 .
b1000 <
b1100 3
b10111 5
b10110 4
b0 1
b0 >
1!
#3260
b1 $
b1 C
b1000110 7
b1000110 A
b111100 6
b111100 @
#3270
b1 -
b1 L
b1100 9
b1100 M
1:
#3280
b100001100000000000000000010100 #
b100001100000000000000000010100 I
b10000 2
b10000 ?
b10000 H
#3300
0!
#3350
b0 %
b0 O
b1 &
b1 N
b10100 "
b10100 D
b0 )
b0 K
b1100 (
b1100 J
0:
b1100000000000000000010100 /
b1100000000000000000010100 =
b10100 *
b10100 ;
b10100 .
b10100 <
b0 3
b0 5
b1100 4
b1000 1
b1000 >
1!
#3360
b0 7
b0 A
b1 6
b1 @
#3380
b100001001101010000000000001011 #
b100001001101010000000000001011 I
b10100 2
b10100 ?
b10100 H
#3400
0!
#3450
b1010 %
b1010 O
b11 &
b11 N
b1011 "
b1011 D
b10101 )
b10101 K
b1001 (
b1001 J
b1001101010000000000001011 /
b1001101010000000000001011 =
b1011 *
b1011 ;
b1011 .
b1011 <
b10101 5
b1001 4
1!
#3460
b1010 7
b1010 A
b11 6
b11 @
#3480
b10101011101100000000000000000 #
b10101011101100000000000000000 I
b1011 2
b1011 ?
b1011 H
#3500
0!
#3550
b111100 %
b111100 O
b10110 )
b10110 K
b1011 (
b1011 J
b1011101100000000000000000 /
b1011101100000000000000000 =
b0 *
b0 ;
b0 .
b0 <
b10110 5
b1011 4
b101 1
b101 >
1!
#3560
b111100 7
b111100 A
#3580
b1000110 -
b1000110 L
b10110 9
b10110 M
1:
#3590
b101011010110000000000000001 #
b101011010110000000000000001 I
b1100 2
b1100 ?
b1100 H
#3600
0!
#3650
b11 %
b11 O
b111101 $
b111101 C
b1011 )
b1011 K
0:
b1011010110000000000000001 /
b1011010110000000000000001 =
b1 *
b1 ;
b1 .
b1 <
b1011 5
b1 1
b1 >
1!
#3660
b100 $
b100 C
b11 7
b11 A
#3670
b100 -
b100 L
b1011 9
b1011 M
1:
#3680
b10101011101110000000000000000 #
b10101011101110000000000000000 I
b1101 2
b1101 ?
b1101 H
#3700
0!
#3750
b1000110 %
b1000110 O
b100 &
b100 N
b10111 )
b10111 K
0:
b1011101110000000000000000 /
b1011101110000000000000000 =
b0 *
b0 ;
b0 .
b0 <
b10111 5
b101 1
b101 >
1!
#3760
b1000110 7
b1000110 A
b100 6
b100 @
#3770
b10100 '
b10100 G
b100 +
b100 E
#3780
b10100 -
b10100 L
b10111 9
b10111 M
1:
#3790
b101001010010000000000000001 #
b101001010010000000000000001 I
b1110 2
b1110 ?
b1110 H
#3800
0!
#3850
b11 %
b11 O
b11 &
b11 N
b1000111 $
b1000111 C
b1001 )
b1001 K
b1001 (
b1001 J
0:
b1001010010000000000000001 /
b1001010010000000000000001 =
b1 *
b1 ;
b1 .
b1 <
b1001 5
b1001 4
b1 1
b1 >
1!
#3860
b100 $
b100 C
b11 7
b11 A
b11 6
b11 @
#3870
b100 -
b100 L
b1001 9
b1001 M
1:
#3880
b10110101110110000000001000 #
b10110101110110000000001000 I
b1111 2
b1111 ?
b1111 H
#3900
0!
#3950
b10100 %
b10100 O
b1000110 &
b1000110 N
b0 $
b0 C
b10111 )
b10111 K
b10110 (
b10110 J
0:
b10110101110110000000001000 /
b10110101110110000000001000 =
b110000000001000 *
b110000000001000 ;
b1000 .
b1000 <
b1100 3
b10111 5
b10110 4
b0 1
b0 >
1!
#3960
b10100 7
b10100 A
b1000110 6
b1000110 @
#3970
b0 -
b0 L
b1100 9
b1100 M
1:
#3980
b100001100000000000000000010100 #
b100001100000000000000000010100 I
b10000 2
b10000 ?
b10000 H
#4000
0!
#4050
b0 %
b0 O
b0 &
b0 N
b10100 "
b10100 D
b0 )
b0 K
b1100 (
b1100 J
0:
b1100000000000000000010100 /
b1100000000000000000010100 =
b10100 *
b10100 ;
b10100 .
b10100 <
b0 3
b0 5
b1100 4
b1000 1
b1000 >
1!
#4060
b10000 "
b10000 D
b0 7
b0 A
b0 6
b0 @
#4080
b10001 "
b10001 D
b11001011101100000000000000000 #
b11001011101100000000000000000 I
b10001 2
b10001 ?
b10001 H
#4100
0!
#4150
b1000110 %
b1000110 O
b100 &
b100 N
b10110 )
b10110 K
b1011 (
b1011 J
b1011101100000000000000000 /
b1011101100000000000000000 =
b0 *
b0 ;
b0 .
b0 <
b10110 5
b1011 4
b110 1
b110 >
1!
#4160
b1000110 7
b1000110 A
b100 6
b100 @
#4170
b1000110 ,
b1000110 F
10
